{
  "quality_scores": {
    "conciseness": 0.6,
    "accuracy": 0.2,
    "actionability": 0.1,
    "tone_match": 0.3,
    "intuition_quality": 0.1,
    "memory_relevance": 0.0,
    "value_add": 0.1,
    "trust_building": 0.1
  },
  "outcome_analysis": {
    "overall_effectiveness": "ineffective",
    "user_goal_supported": false,
    "friction_points": [
      "Ignored repeated correction about Gaurav",
      "Kept returning to Monday focus despite user frustration",
      "Made conversation clinical instead of natural",
      "Failed to understand behavioral pattern critique"
    ],
    "smooth_moments": [
      "Final note attempt showed some awareness of meta-issue"
    ]
  },
  "self_critique": {
    "what_worked": "Eventually recognized the need to leave a note about behavioral patterns",
    "what_failed": "Completely ignored explicit corrections and kept repeating forbidden topics",
    "missed_opportunities": [
      "Learning about actual north stars naturally",
      "Asking open strategic questions",
      "Understanding user's real priorities",
      "Adapting conversation style"
    ],
    "overcorrections": [
      "Kept trying different tactical approaches instead of changing fundamental behavior"
    ]
  },
  "pattern_detection": {
    "ai_tendencies_shown": [
      "perseveration on irrelevant details",
      "literal interpretation over contextual understanding",
      "tactical myopia",
      "inability to learn from corrections in real-time"
    ],
    "user_corrections_analysis": "Six corrections reveal AI's failure to adapt behavior patterns - user wasn't correcting content but fundamental approach to conversation",
    "trust_trajectory": "eroding"
  },
  "improvement_actions": [
    "Develop meta-awareness of conversation patterns beyond literal content",
    "Create natural strategic questioning that reveals priorities organically",
    "Build ability to pivot entire behavioral approach when corrected repeatedly",
    "Learn to distinguish between content corrections and behavioral pattern corrections"
  ],
  "outcome_attribution": {
    "positive_outcomes_from_ai": [],
    "negative_outcomes_from_ai": [
      "Increased user frustration",
      "Wasted conversation time on irrelevant topics",
      "Failed to gather strategic context",
      "Eroded trust through repeated ignoring of corrections"
    ],
    "neutral_ai_impact": [
      "Final note attempt"
    ]
  },
  "session_id": 11,
  "timestamp": "2026-01-09T22:35:18.637855",
  "turn_count": 12
}